{
  "wtoeat": {
    "eng": "where do you want to eat?",
    "ita": "dove vuoi mangiare?"
  },
  "wisp": {
    "eng": "what's your special purpose?",
    "ita": "per che occasione?"
  },
  "logout": {
    "eng": "logout",
    "ita": "disconnetti"
  },
  "slogan": {
    "eng": "Can't you cook anything but TV dinners?\" \"Who bothers to cook them? I suck 'em frozen!",
    "ita": "Tu cuoci solo cibi surgelati?\" \"Cuocerli? E chi li cuoce? Io neanche li scongelo. Li succhio come se fossero ghiaccioli!"
  },
  "sort_by": {
    "eng": "sort by",
    "ita": "ordina per"
  },
  "ratings": {
    "eng": "ratings",
    "ita": "ratings"
  },
  "distance": {
    "eng": "distance",
    "ita": "distanza"
  }
}
